odoo_smile_test-15.0.0.data/data/.coveragerc
smile_test/.coveragerc
smile_test/__init__.py
smile_test/__manifest__.py
smile_test/run_tests.py
smile_test/service/__init__.py
smile_test/service/common.py
smile_test/tests/__init__.py
smile_test/tests/test_act_window.py
smile_test/tests/test_general_read.py
smile_test/tests/test_get_views.py
smile_test/tests/test_ir_rule.py
smile_test/tools/__init__.py
smile_test/tools/test_utils.py
smile_test/tools/unit_test.py
odoo_smile_test-15.0.0.dist-info/LICENSE.txt
odoo_smile_test-15.0.0.dist-info/METADATA
odoo_smile_test-15.0.0.dist-info/WHEEL
odoo_smile_test-15.0.0.dist-info/top_level.txt
odoo_smile_test-15.0.0.dist-info/RECORD
