Metadata-Version: 2.1
Name: odoo-smile-test
Version: 15.0.0
Summary: Smile test module
Author: Smile
Author-email: martin.deconinck@smile.fr
License: LGPL
Keywords: odoo,test,smile_test,smile
Classifier: Development Status :: 3 - Alpha
Classifier: Intended Audience :: Developers
Classifier: Topic :: Software Development :: Build Tools
Classifier: License :: OSI Approved :: GNU Lesser General Public License v3 (LGPLv3)
Classifier: Programming Language :: Python :: 3
Classifier: Programming Language :: Python :: 3.4
Classifier: Programming Language :: Python :: 3.5
Classifier: Programming Language :: Python :: 3.6
License-File: LICENSE.txt
Requires-Dist: coverage
Requires-Dist: flake8
Requires-Dist: unittest2
Requires-Dist: pycobertura
Requires-Dist: xmlrunner
Requires-Dist: debugpy
